nacre/__init__.py
nacre/actors/__init__.pxd
nacre/actors/__init__.py
nacre/actors/exposer.cpython-310-darwin.so
nacre/actors/exposer.pxd
nacre/actors/exposer.pyx
nacre/actors/pubsub.cpython-310-darwin.so
nacre/actors/pubsub.pxd
nacre/actors/pubsub.pyx
nacre/adapters/__init__.py
nacre/adapters/binance/__init__.py
nacre/adapters/binance/factories.py
nacre/adapters/binance/parsing.py
nacre/adapters/utils.py
nacre/adapters/zb/__init__.py
nacre/adapters/zb/common/__init__.py
nacre/adapters/zb/common/enums.py
nacre/adapters/zb/config.py
nacre/adapters/zb/data.py
nacre/adapters/zb/data_types.py
nacre/adapters/zb/factories.py
nacre/adapters/zb/futures/__init__.py
nacre/adapters/zb/futures/execution.py
nacre/adapters/zb/http/__init__.py
nacre/adapters/zb/http/api/__init__.py
nacre/adapters/zb/http/api/future_account.py
nacre/adapters/zb/http/api/future_market.py
nacre/adapters/zb/http/api/spot_account.py
nacre/adapters/zb/http/api/spot_market.py
nacre/adapters/zb/http/client.py
nacre/adapters/zb/http/error.py
nacre/adapters/zb/http/spot.py
nacre/adapters/zb/parsing.py
nacre/adapters/zb/providers.py
nacre/adapters/zb/spot/__init__.py
nacre/adapters/zb/spot/execution.py
nacre/adapters/zb/websocket/__init__.py
nacre/adapters/zb/websocket/client.py
nacre/adapters/zb/websocket/futures.py
nacre/adapters/zb/websocket/spot.py
nacre/config/__init__.pxd
nacre/config/__init__.py
nacre/config/actors.py
nacre/config/live.py
nacre/config/nodes.py
nacre/console/__init__.py
nacre/console/cli.py
nacre/examples/__init__.py
nacre/examples/live/mon.py
nacre/examples/live/mon.yml
nacre/examples/strategies/__init__.py
nacre/examples/strategies/mon.py
nacre/execution/__init__.pxd
nacre/execution/reports.cpython-310-darwin.so
nacre/execution/reports.pxd
nacre/execution/reports.pyx
nacre/indicators/__init__.py
nacre/indicators/avl.cpython-310-darwin.so
nacre/indicators/avl.pxd
nacre/indicators/avl.pyx
nacre/indicators/bar_min_max.cpython-310-darwin.so
nacre/indicators/bar_min_max.pxd
nacre-0.2.26.dist-info/entry_points.txt
nacre-0.2.26.dist-info/WHEEL
nacre-0.2.26.dist-info/METADATA
nacre-0.2.26.dist-info/RECORD
