Metadata-Version: 2.1
Name: nacre
Version: 0.2.26
Summary: Nacre
Author: Sidn
Author-email: sidnvy@gmail.com
Requires-Python: >=3.8,<3.11
Classifier: Programming Language :: Python :: 3
Classifier: Programming Language :: Python :: 3.8
Classifier: Programming Language :: Python :: 3.9
Classifier: Programming Language :: Python :: 3.10
Requires-Dist: PyYAML (>=6.0,<7.0)
Requires-Dist: aiokafka (>=0.7.2,<0.8.0)
Requires-Dist: fastavro (>=1.4.6,<2.0.0)
Requires-Dist: fire (>=0.4.0,<0.5.0)
Requires-Dist: grpcio (>=1.40.0,<2.0.0)
Requires-Dist: hiredis (>=2.0.0,<3.0.0)
Requires-Dist: importlib-metadata (>=4.12.0,<5.0.0)
Requires-Dist: msgpack (>=1.0.3,<2.0.0)
Requires-Dist: nautilus-trader (==1.152.0)
Requires-Dist: orjson (>=3.7.11,<4.0.0)
Requires-Dist: prometheus-async[aiohttp] (>=19.2.0,<20.0.0)
Requires-Dist: python-schema-registry-client (>=2.2.0,<3.0.0)
Requires-Dist: redis (>=4.2.2,<5.0.0)
Requires-Dist: requests (>=2.28.1,<3.0.0)
Requires-Dist: tenacity (>=8.0.1,<9.0.0)
Requires-Dist: urllib3 (>=1.26.12,<2.0.0)
